[{"İlçe Kodu":"1296","İlçe Adı":"EFLANİ","Sandık Sayısı":"62","Kayıtlı Seçmen Sayısı":"6.824","Oy Kullanan Seçmen Sayısı":"5.342","Katılım Oranı":"%78,28","Geçerli Oy Sayısı":"5.189","Geçerli Oy Oranı":"%97,14","Geçersiz Oy Sayısı":"153","Geçersiz Oy Oranı":"%2,86","Evet Sayısı":"3.926","Evet Oranı":"%75,66","Hayır Sayısı":"1.263","Hayır Oranı":"%24,34","Mahaller Bazlı Veri İndir":" Excel İndir  Json İndir "},{"İlçe Kodu":"1321","İlçe Adı":"ESKİPAZAR","Sandık Sayısı":"65","Kayıtlı Seçmen Sayısı":"9.730","Oy Kullanan Seçmen Sayısı":"8.119","Katılım Oranı":"%83,44","Geçerli Oy Sayısı":"7.904","Geçerli Oy Oranı":"%97,35","Geçersiz Oy Sayısı":"215","Geçersiz Oy Oranı":"%2,65","Evet Sayısı":"5.792","Evet Oranı":"%73,28","Hayır Sayısı":"2.112","Hayır Oranı":"%26,72","Mahaller Bazlı Veri İndir":" Excel İndir  Json İndir "},{"İlçe Kodu":"1433","İlçe Adı":"KARABÜK MERKEZ","Sandık Sayısı":"265","Kayıtlı Seçmen Sayısı":"92.121","Oy Kullanan Seçmen Sayısı":"80.731","Katılım Oranı":"%87,64","Geçerli Oy Sayısı":"79.187","Geçerli Oy Oranı":"%98,09","Geçersiz Oy Sayısı":"1.544","Geçersiz Oy Oranı":"%1,91","Evet Sayısı":"49.051","Evet Oranı":"%61,94","Hayır Sayısı":"30.136","Hayır Oranı":"%38,06","Mahaller Bazlı Veri İndir":" Excel İndir  Json İndir "},{"İlçe Kodu":"1561","İlçe Adı":"OVACIK","Sandık Sayısı":"44","Kayıtlı Seçmen Sayısı":"2.616","Oy Kullanan Seçmen Sayısı":"2.305","Katılım Oranı":"%88,11","Geçerli Oy Sayısı":"2.232","Geçerli Oy Oranı":"%96,83","Geçersiz Oy Sayısı":"73","Geçersiz Oy Oranı":"%3,17","Evet Sayısı":"1.599","Evet Oranı":"%71,64","Hayır Sayısı":"633","Hayır Oranı":"%28,36","Mahaller Bazlı Veri İndir":" Excel İndir  Json İndir "},{"İlçe Kodu":"1587","İlçe Adı":"SAFRANBOLU","Sandık Sayısı":"169","Kayıtlı Seçmen Sayısı":"44.763","Oy Kullanan Seçmen Sayısı":"39.246","Katılım Oranı":"%87,68","Geçerli Oy Sayısı":"38.463","Geçerli Oy Oranı":"%98","Geçersiz Oy Sayısı":"783","Geçersiz Oy Oranı":"%2","Evet Sayısı":"20.901","Evet Oranı":"%54,34","Hayır Sayısı":"17.562","Hayır Oranı":"%45,66","Mahaller Bazlı Veri İndir":" Excel İndir  Json İndir "},{"İlçe Kodu":"1856","İlçe Adı":"YENİCE","Sandık Sayısı":"69","Kayıtlı Seçmen Sayısı":"16.588","Oy Kullanan Seçmen Sayısı":"14.317","Katılım Oranı":"%86,31","Geçerli Oy Sayısı":"13.637","Geçerli Oy Oranı":"%95,25","Geçersiz Oy Sayısı":"680","Geçersiz Oy Oranı":"%4,75","Evet Sayısı":"7.762","Evet Oranı":"%56,92","Hayır Sayısı":"5.875","Hayır Oranı":"%43,08","Mahaller Bazlı Veri İndir":" Excel İndir  Json İndir "}]